{
    "display": {
      "icon": {
        "item": "minecraft:deepslate_coal_ore"
      },
      "title": {
        "text": "这种方块是真实存在的吗？",
        "color": "dark_gray",
        "bold": true
      },
      "description": {
        "text": "在地底挖到一个深层煤矿石",
        "italic": true
      },
      "frame": "challenge",
      "show_toast": true,
      "announce_to_chat": true,
      "hidden": false
    },
    "parent": "bakamc:get_deepslate",
    "criteria": {
      "get_deepslate_coal_ore": {
        "trigger": "minecraft:inventory_changed",
        "conditions": {
          "player": {
            "location": {
              "position": {
                "y": {
                  "min": -100,
                  "max": 5
                }
              }
            }
          },
          "items": [
            {
              "items": [
                "minecraft:deepslate_coal_ore"
              ],
              "count": 1
            }
          ]
        }
      }
    }
  }
  